{
	"users": [
		{
			"id": "x8q2m9a1",
			"name": "Liam Foster",
			"company": "NovaByte Ltd",
			"country": { "name": "United States", "flag": "us" },
			"mobile": "(415) 729-1842"
		},
		{
			"id": "k9p2xq8m",
			"name": "Elena Brooks",
			"company": "Skyline Systems",
			"country": { "name": "Canada", "flag": "ca" },
			"mobile": "(647) 381-9204"
		},
		{
			"id": "a7m9xq2k",
			"name": "Arjun Mehta",
			"company": "PixelForge",
			"country": { "name": "India", "flag": "in" },
			"mobile": "(+91) 98231-44720"
		},
		{
			"id": "m2x9q7p1",
			"name": "Sofia Alvarez",
			"company": "BrightWave Corp",
			"country": { "name": "Spain", "flag": "es" },
			"mobile": "(+34) 612-884-930"
		},
		{
			"id": "q8m2k9x1",
			"name": "Daniel Wu",
			"company": "CloudNest",
			"country": { "name": "Singapore", "flag": "sg" },
			"mobile": "(+65) 9123-4481"
		},
		{
			"id": "p7x9k2m1",
			"name": "Noah Grant",
			"company": "IronPeak Solutions",
			"country": { "name": "United Kingdom", "flag": "gb" },
			"mobile": "(+44) 7700-918442"
		},
		{
			"id": "9kq2m8x1",
			"name": "Mia Johansson",
			"company": "Nordic Pulse",
			"country": { "name": "Sweden", "flag": "se" },
			"mobile": "(+46) 703-889-221"
		},
		{
			"id": "m1x9q8k2",
			"name": "Lucas Martin",
			"company": "EchoLine Tech",
			"country": { "name": "France", "flag": "fr" },
			"mobile": "(+33) 674-553-219"
		},
		{
			"id": "k8x9q2m1",
			"name": "Ava Collins",
			"company": "BlueOrbit",
			"country": { "name": "Australia", "flag": "au" },
			"mobile": "(+61) 412-883-104"
		},
		{
			"id": "q9k2x8m1",
			"name": "Ethan Novak",
			"company": "ZenithWare",
			"country": { "name": "Germany", "flag": "de" },
			"mobile": "(+49) 176-9021-4483"
		},
		{
			"id": "xq82m91k",
			"name": "Isabella Romano",
			"company": "Aurora Labs",
			"country": { "name": "Italy", "flag": "it" },
			"mobile": "(+39) 347-552-9102"
		},
		{
			"id": "p9m2k1xq",
			"name": "Hiro Tanaka",
			"company": "NextGen Works",
			"country": { "name": "Japan", "flag": "jp" },
			"mobile": "(+81) 90-3321-8894"
		},
		{
			"id": "kq92x8m1",
			"name": "Oliver Reed",
			"company": "VertexCore",
			"country": { "name": "Ireland", "flag": "ie" },
			"mobile": "(+353) 87-221-9841"
		},
		{
			"id": "m8q1x9k2",
			"name": "Chloe Bernard",
			"company": "LumenSoft",
			"country": { "name": "Belgium", "flag": "be" },
			"mobile": "(+32) 472-883-219"
		},
		{
			"id": "x2k9q8m1",
			"name": "Mateo Silva",
			"company": "Orbitronix",
			"country": { "name": "Brazil", "flag": "br" },
			"mobile": "(+55) 21-98831-4472"
		},
		{
			"id": "q8x2m9k1",
			"name": "Nina Petrov",
			"company": "Baltic Systems",
			"country": { "name": "Estonia", "flag": "ee" },
			"mobile": "(+372) 5321-8894"
		},
		{
			"id": "m1k9q8x2",
			"name": "Omar Hassan",
			"company": "DesertLink",
			"country": { "name": "UAE", "flag": "ae" },
			"mobile": "(+971) 55-883-2194"
		},
		{
			"id": "xq91m8k2",
			"name": "Sara Lindholm",
			"company": "FjordTech",
			"country": { "name": "Norway", "flag": "no" },
			"mobile": "(+47) 921-883-104"
		},
		{
			"id": "k2x9m1q8",
			"name": "Pedro Costa",
			"company": "AtlanticSoft",
			"country": { "name": "Portugal", "flag": "pt" },
			"mobile": "(+351) 912-884-441"
		},
		{
			"id": "m9x1q8k2",
			"name": "Yara Nasser",
			"company": "CedarStack",
			"country": { "name": "Lebanon", "flag": "lb" },
			"mobile": "(+961) 71-883-221"
		},
		{
			"id": "q7x9m2k1",
			"name": "Alex Turner",
			"company": "CoreAxis",
			"country": { "name": "United States", "flag": "us" },
			"mobile": "(212) 883-1942"
		},
		{
			"id": "m8x1q9k2",
			"name": "Ritika Sharma",
			"company": "DataSpire",
			"country": { "name": "India", "flag": "in" },
			"mobile": "(+91) 99102-33418"
		},
		{
			"id": "k9x2m1q8",
			"name": "Jonas Müller",
			"company": "RheinCode",
			"country": { "name": "Germany", "flag": "de" },
			"mobile": "(+49) 151-7721-9304"
		},
		{
			"id": "x8k9m2q1",
			"name": "Laura Gomez",
			"company": "Solstice Tech",
			"country": { "name": "Mexico", "flag": "mx" },
			"mobile": "(+52) 55-8834-1920"
		},
		{
			"id": "q2m9x8k1",
			"name": "Samuel Okoye",
			"company": "NexaGrid",
			"country": { "name": "Nigeria", "flag": "ng" },
			"mobile": "(+234) 803-991-4482"
		},
		{
			"id": "m9k1x8q2",
			"name": "Wei Zhang",
			"company": "SilkRoute Labs",
			"country": { "name": "China", "flag": "cn" },
			"mobile": "(+86) 138-7721-8841"
		},
		{
			"id": "k1x9q2m8",
			"name": "Fatima Al Noor",
			"company": "PearlNet",
			"country": { "name": "Qatar", "flag": "qa" },
			"mobile": "(+974) 5518-2291"
		},
		{
			"id": "x9q8k1m2",
			"name": "Andrei Popescu",
			"company": "Danube Systems",
			"country": { "name": "Romania", "flag": "ro" },
			"mobile": "(+40) 721-884-913"
		},
		{
			"id": "m2k9x8q1",
			"name": "Grace O’Connell",
			"company": "Emerald Stack",
			"country": { "name": "Ireland", "flag": "ie" },
			"mobile": "(+353) 86-772-4491"
		},
		{
			"id": "q9x1m2k8",
			"name": "Victor Hansen",
			"company": "PolarSoft",
			"country": { "name": "Denmark", "flag": "dk" },
			"mobile": "(+45) 281-993-104"
		}
	]
}
